ollamatools.py
ollama_tool_cli-1.1.1.dist-info/METADATA
ollama_tool_cli-1.1.1.dist-info/WHEEL
ollama_tool_cli-1.1.1.dist-info/entry_points.txt
ollama_tool_cli-1.1.1.dist-info/top_level.txt
ollama_tool_cli-1.1.1.dist-info/RECORD
