Metadata-Version: 2.4
Name: ollama-tool-cli
Version: 1.1.1
Summary: CLI tool for managing Ollama models - backup, restore, update, and list models
Author-email: Arian Omrani <arianomrani24@gmail.com>
License-Expression: MIT
Project-URL: Homepage, https://github.com/arian24b/ollamatools
Project-URL: Repository, https://github.com/arian24b/ollamatools
Project-URL: Issues, https://github.com/arian24b/ollamatools/issues
Keywords: ollama,cli,models,backup,restore,llm
Classifier: Development Status :: 3 - Alpha
Classifier: Intended Audience :: Developers
Classifier: Operating System :: OS Independent
Classifier: Programming Language :: Python :: 3
Classifier: Programming Language :: Python :: 3.10
Classifier: Programming Language :: Python :: 3.11
Classifier: Programming Language :: Python :: 3.12
Classifier: Programming Language :: Python :: 3.13
Classifier: Programming Language :: Python :: 3.14
Requires-Python: >=3.10
Requires-Dist: typer>=0.12.0
Provides-Extra: dev
Requires-Dist: ruff; extra == "dev"
Requires-Dist: pytest; extra == "dev"
Requires-Dist: build; extra == "dev"
